{
  "_class": "group",
  "do_objectID": "A9B70022-764E-4226-B65C-DB08EE40179C",
  "exportOptions": {
    "_class": "exportOptions",
    "exportFormats": [
    ],
    "includedLayerIds": [
    ],
    "layerOptions": 0,
    "shouldTrim": false
  },
  "frame": {
    "_class": "rect",
    "constrainProportions": false,
    "height": 445,
    "width": 486,
    "x": 754,
    "y": 382
  },
  "hasClickThrough": false,
  "isFlippedHorizontal": false,
  "isFlippedVertical": false,
  "isLocked": false,
  "isVisible": true,
  "layerListExpandedType": 0,
  "layers": [
    {
      "class": "shapeGroup",
      "id": "274AD8C4-F1E4-48CA-8A43-3A30FC368263"
    },
    {
      "class": "symbolInstance",
      "id": "84283BCB-83A0-4114-8A5F-B7A6597B2057"
    },
    {
      "class": "symbolInstance",
      "id": "BA16E831-650F-4DA8-A912-54DD0E0FDF26"
    },
    {
      "class": "symbolInstance",
      "id": "343210B9-A1A3-4309-BB76-701B5DA27C18"
    },
    {
      "class": "symbolInstance",
      "id": "B2D76B88-A5A8-4372-A0CD-047D818481E1"
    },
    {
      "class": "symbolInstance",
      "id": "2DE30713-3F56-4F7F-BDAE-5E3731C5410C"
    },
    {
      "class": "symbolInstance",
      "id": "258EADEF-BB5E-4F9F-AA9F-D79B0D781D83"
    },
    {
      "class": "symbolInstance",
      "id": "6DAB5ACA-6A1B-4A21-82C6-988785D2BB32"
    },
    {
      "class": "symbolInstance",
      "id": "B4D7329E-7D15-4FFE-B788-37A2B8CAAC32"
    },
    {
      "class": "symbolInstance",
      "id": "41437B68-A6F0-483E-9726-E6AA3AE676A6"
    },
    {
      "class": "symbolInstance",
      "id": "40354443-8481-4AA6-9563-1FE67BBE3448"
    }
  ],
  "name": "Price Table",
  "nameIsFixed": true,
  "resizingConstraint": 63,
  "resizingType": 0,
  "rotation": 0,
  "shouldBreakMaskChain": false,
  "style": {
    "_class": "style",
    "endDecorationType": 0,
    "miterLimit": 10,
    "startDecorationType": 0
  }
}