{
  "_class": "rectangle",
  "booleanOperation": -1,
  "do_objectID": "84106D01-D848-4E59-8084-DB740C83E768",
  "edited": true,
  "exportOptions": {
    "_class": "exportOptions",
    "exportFormats": [
    ],
    "includedLayerIds": [
    ],
    "layerOptions": 0,
    "shouldTrim": false
  },
  "fixedRadius": 3,
  "frame": {
    "_class": "rect",
    "constrainProportions": false,
    "height": 49.99999999999999,
    "width": 193.0756972111546,
    "x": 0,
    "y": -3.197442310920451e-14
  },
  "hasConvertedToNewRoundCorners": true,
  "isFlippedHorizontal": false,
  "isFlippedVertical": false,
  "isLocked": false,
  "isVisible": true,
  "layerListExpandedType": 0,
  "name": "Path",
  "nameIsFixed": false,
  "path": {
    "_class": "path",
    "isClosed": true,
    "pointRadiusBehaviour": 1,
    "points": [
      {
        "_class": "curvePoint",
        "cornerRadius": 0,
        "curveFrom": "{0, 3.2742575688747474e-06}",
        "curveMode": 1,
        "curveTo": "{0, 3.2742575688747474e-06}",
        "hasCurveFrom": false,
        "hasCurveTo": false,
        "point": "{0, 3.2742575688747474e-06}"
      },
      {
        "_class": "curvePoint",
        "cornerRadius": 3,
        "curveFrom": "{0.99999999999999989, 3.2742575689013934e-06}",
        "curveMode": 1,
        "curveTo": "{0.99999999999999989, 3.2742575689013934e-06}",
        "hasCurveFrom": false,
        "hasCurveTo": false,
        "point": "{0.99999999999999989, 3.2742575689013934e-06}"
      },
      {
        "_class": "curvePoint",
        "cornerRadius": 3,
        "curveFrom": "{0.99999999999999989, 1.0000000000000002}",
        "curveMode": 1,
        "curveTo": "{0.99999999999999989, 1.0000000000000002}",
        "hasCurveFrom": false,
        "hasCurveTo": false,
        "point": "{0.99999999999999989, 1.0000000000000002}"
      },
      {
        "_class": "curvePoint",
        "cornerRadius": 0,
        "curveFrom": "{0, 1}",
        "curveMode": 1,
        "curveTo": "{0, 1}",
        "hasCurveFrom": false,
        "hasCurveTo": false,
        "point": "{0, 1}"
      }
    ]
  },
  "resizingConstraint": 63,
  "resizingType": 0,
  "rotation": 0,
  "shouldBreakMaskChain": false
}