{
  "_class": "shapePath",
  "booleanOperation": -1,
  "do_objectID": "7BC968CD-4188-4ECD-8BA0-2442C7F7C143",
  "edited": true,
  "exportOptions": {
    "_class": "exportOptions",
    "exportFormats": [
    ],
    "includedLayerIds": [
    ],
    "layerOptions": 0,
    "shouldTrim": false
  },
  "frame": {
    "_class": "rect",
    "constrainProportions": false,
    "height": 7.000000000000091,
    "width": 4.999999999999992,
    "x": 0,
    "y": 0
  },
  "isFlippedHorizontal": false,
  "isFlippedVertical": false,
  "isLocked": false,
  "isVisible": true,
  "layerListExpandedType": 0,
  "name": "Path",
  "nameIsFixed": false,
  "path": {
    "_class": "path",
    "isClosed": true,
    "pointRadiusBehaviour": 1,
    "points": [
      {
        "_class": "curvePoint",
        "cornerRadius": 0,
        "curveFrom": "{0.51263714733542332, 0.96019388954171569}",
        "curveMode": 4,
        "curveTo": "{0.60511363636363602, 0.88050822561692133}",
        "hasCurveFrom": true,
        "hasCurveTo": false,
        "point": "{0.60511363636363602, 0.88050822561692133}"
      },
      {
        "_class": "curvePoint",
        "cornerRadius": 0,
        "curveFrom": "{0.22492163009404439, 1}",
        "curveMode": 3,
        "curveTo": "{0.41604623824451387, 1}",
        "hasCurveFrom": true,
        "hasCurveTo": true,
        "point": "{0.31514498432601923, 1}"
      },
      {
        "_class": "curvePoint",
        "cornerRadius": 0,
        "curveFrom": "{0.02997648902821359, 0.87529377203290248}",
        "curveMode": 2,
        "curveTo": "{0.14998040752351147, 0.9750293772032903}",
        "hasCurveFrom": true,
        "hasCurveTo": true,
        "point": "{0.089929467084640072, 0.92516157461809634}"
      },
      {
        "_class": "curvePoint",
        "cornerRadius": 0,
        "curveFrom": "{0, 0.62125440658049358}",
        "curveMode": 2,
        "curveTo": "{0, 0.80295240893066977}",
        "hasCurveFrom": true,
        "hasCurveTo": true,
        "point": "{0, 0.70806404230317277}"
      },
      {
        "_class": "curvePoint",
        "cornerRadius": 0,
        "curveFrom": "{0.1185344827586207, 0.39835487661574615}",
        "curveMode": 2,
        "curveTo": "{0.023804858934169473, 0.54193595769682723}",
        "hasCurveFrom": true,
        "hasCurveTo": true,
        "point": "{0.071218652037617888, 0.47010869565217389}"
      },
      {
        "_class": "curvePoint",
        "cornerRadius": 0,
        "curveFrom": "{0.32063087774294685, 0.27291421856639259}",
        "curveMode": 2,
        "curveTo": "{0.17799764890282124, 0.34452115158636892}",
        "hasCurveFrom": true,
        "hasCurveTo": true,
        "point": "{0.24931426332288403, 0.30875440658049358}"
      },
      {
        "_class": "curvePoint",
        "cornerRadius": 0,
        "curveFrom": "{0.58189655172413812, 0.25506756756756749}",
        "curveMode": 3,
        "curveTo": "{0.39204545454545459, 0.25506756756756749}",
        "hasCurveFrom": true,
        "hasCurveTo": true,
        "point": "{0.46375391849529773, 0.25506756756756749}"
      },
      {
        "_class": "curvePoint",
        "cornerRadius": 0,
        "curveFrom": "{0.73138714733542287, 0.38322561692126911}",
        "curveMode": 4,
        "curveTo": "{0.67114028213166166, 0.29773795534665104}",
        "hasCurveFrom": false,
        "hasCurveTo": true,
        "point": "{0.73138714733542287, 0.38322561692126911}"
      },
      {
        "_class": "curvePoint",
        "cornerRadius": 0,
        "curveFrom": "{0.83885188087774276, 0}",
        "curveMode": 1,
        "curveTo": "{0.83885188087774276, 0}",
        "hasCurveFrom": false,
        "hasCurveTo": false,
        "point": "{0.83885188087774276, 0}"
      },
      {
        "_class": "curvePoint",
        "cornerRadius": 0,
        "curveFrom": "{1, 0}",
        "curveMode": 1,
        "curveTo": "{1, 0}",
        "hasCurveFrom": false,
        "hasCurveTo": false,
        "point": "{1, 0}"
      },
      {
        "_class": "curvePoint",
        "cornerRadius": 0,
        "curveFrom": "{0.72609717868338575, 0.98391598119858992}",
        "curveMode": 1,
        "curveTo": "{0.72609717868338575, 0.98391598119858992}",
        "hasCurveFrom": false,
        "hasCurveTo": false,
        "point": "{0.72609717868338575, 0.98391598119858992}"
      },
      {
        "_class": "curvePoint",
        "cornerRadius": 0,
        "curveFrom": "{0.57650862068965536, 0.98391598119858992}",
        "curveMode": 1,
        "curveTo": "{0.57650862068965536, 0.98391598119858992}",
        "hasCurveFrom": false,
        "hasCurveTo": false,
        "point": "{0.57650862068965536, 0.98391598119858992}"
      }
    ]
  },
  "resizingConstraint": 63,
  "resizingType": 0,
  "rotation": 0,
  "shouldBreakMaskChain": false
}